tls_probe.py
tls_probe-1.3.0.dist-info/LICENSE
tls_probe-1.3.0.dist-info/METADATA
tls_probe-1.3.0.dist-info/WHEEL
tls_probe-1.3.0.dist-info/entry_points.txt
tls_probe-1.3.0.dist-info/top_level.txt
tls_probe-1.3.0.dist-info/RECORD
