Metadata-Version: 2.1
Name: tls-probe
Version: 1.3.0
Summary: probe specified SSL/TLS service and return information
Home-page: https://github.com/dspruell/tls-probe
Author: Darren Spruell
Author-email: dspruell@sancho2k.net
License: ISC
Classifier: Development Status :: 5 - Production/Stable
Classifier: Environment :: Console
Classifier: Intended Audience :: Information Technology
Classifier: License :: OSI Approved :: ISC License (ISCL)
Classifier: Operating System :: POSIX
Classifier: Programming Language :: Python :: 3
Classifier: Topic :: Security
Classifier: Topic :: System :: Networking :: Monitoring
License-File: LICENSE
Requires-Dist: cryptography>=42
Requires-Dist: pyjarm<=0.1.0
Requires-Dist: tabulate
